LICENSE
MANIFEST.in
README.md
setup.py
exhaust_ma/__init__.py
exhaust_ma/__main__.py
exhaust_ma/build_cffi.py
exhaust_ma/core.py
exhaust_ma/warrior.py
exhaust_ma.egg-info/PKG-INFO
exhaust_ma.egg-info/SOURCES.txt
exhaust_ma.egg-info/dependency_links.txt
exhaust_ma.egg-info/requires.txt
exhaust_ma.egg-info/top_level.txt
exhaust_ma/exhaust-ma/.git
exhaust_ma/exhaust-ma/COPYING
exhaust_ma/exhaust-ma/Makefile
exhaust_ma/exhaust-ma/NEWS
exhaust_ma/exhaust-ma/README
exhaust_ma/exhaust-ma/README.md
exhaust_ma/exhaust-ma/asm.c
exhaust_ma/exhaust-ma/asm.h
exhaust_ma/exhaust-ma/bench.sh
exhaust_ma/exhaust-ma/benchmark.txt
exhaust_ma/exhaust-ma/changelog
exhaust_ma/exhaust-ma/exhaust.c
exhaust_ma/exhaust-ma/exhaust.h
exhaust_ma/exhaust-ma/fixed.rc
exhaust_ma/exhaust-ma/imp.rc
exhaust_ma/exhaust-ma/insn.h
exhaust_ma/exhaust-ma/jaguar.rc
exhaust_ma/exhaust-ma/npaper2.rc
exhaust_ma/exhaust-ma/pspace.c
exhaust_ma/exhaust-ma/pspace.h
exhaust_ma/exhaust-ma/sim.c
exhaust_ma/exhaust-ma/sim.h
exhaust_ma/exhaust-ma/spl.rc
exhaust_ma/exhaust-ma/stalker.rc
exhaust_ma/exhaust-ma/test.pl