Metadata-Version: 1.0
Name: exhaust-ma
Version: 0.0.3
Summary: Fast CoreWars redcode simulator, python bindings.
Home-page: UNKNOWN
Author: Lieuwe Mosch
Author-email: lieuwemo@gmail.com
License: UNKNOWN
Keywords: corewars redcode mars
Platform: UNKNOWN
